<Root><AggregatedData><Podkategoria>Mike Shema</Podkategoria><TotalQuantity>319</TotalQuantity><TotalRevenue>11616.5</TotalRevenue><AverageTotalQuantity>2.4166666666666665</AverageTotalQuantity><AverageTotalRevenue>88.003787878787875</AverageTotalRevenue><Books><Id>9</Id><Name>Hacking Web Apps</Name><TotalQuantity>254</TotalQuantity><TotalRevenue>10414</TotalRevenue><AverageTotalQuantity>1.9242424242424243</AverageTotalQuantity><AverageTotalRevenue>78.893939393939391</AverageTotalRevenue></Books><Books><Id>10</Id><Name>Hacking bez tajemství - Webové aplikace</Name><TotalQuantity>65</TotalQuantity><TotalRevenue>1202.5</TotalRevenue><AverageTotalQuantity>0.49242424242424243</AverageTotalQuantity><AverageTotalRevenue>9.1098484848484844</AverageTotalRevenue></Books></AggregatedData><AggregatedData><Podkategoria>Dale Carnegie</Podkategoria><TotalQuantity>364</TotalQuantity><TotalRevenue>6372.2999999999993</TotalRevenue><AverageTotalQuantity>2.7575757575757578</AverageTotalQuantity><AverageTotalRevenue>48.274999999999991</AverageTotalRevenue><Books><Id>21</Id><Name>Ako sa zbaviť starostí a začať žiť</Name><TotalQuantity>218</TotalQuantity><TotalRevenue>4905</TotalRevenue><AverageTotalQuantity>1.6515151515151516</AverageTotalQuantity><AverageTotalRevenue>37.159090909090907</AverageTotalRevenue></Books><Books><Id>20</Id><Name>Ako si získavať priateľov a pôsobiť na ľudí</Name><TotalQuantity>146</TotalQuantity><TotalRevenue>1467.2999999999997</TotalRevenue><AverageTotalQuantity>1.106060606060606</AverageTotalQuantity><AverageTotalRevenue>11.115909090909089</AverageTotalRevenue></Books></AggregatedData><AggregatedData><Podkategoria>Jaroslava Lukačovičová</Podkategoria><TotalQuantity>324</TotalQuantity><TotalRevenue>4879.2800000000016</TotalRevenue><AverageTotalQuantity>2.4545454545454546</AverageTotalQuantity><AverageTotalRevenue>36.964242424242435</AverageTotalRevenue><Books><Id>24</Id><Name>Šlabikár financií pre neziskovky</Name><TotalQuantity>188</TotalQuantity><TotalRevenue>3568.2400000000002</TotalRevenue><AverageTotalQuantity>1.4242424242424243</AverageTotalQuantity><AverageTotalRevenue>27.032121212121215</AverageTotalRevenue></Books><Books><Id>3</Id><Name>Jednoduché účtovníctvo pre neziskovky</Name><TotalQuantity>136</TotalQuantity><TotalRevenue>1311.04</TotalRevenue><AverageTotalQuantity>1.0303030303030303</AverageTotalQuantity><AverageTotalRevenue>9.9321212121212117</AverageTotalRevenue></Books></AggregatedData><AggregatedData><Podkategoria>Julie Caplin</Podkategoria><TotalQuantity>325</TotalQuantity><TotalRevenue>4580.7700000000013</TotalRevenue><AverageTotalQuantity>2.4621212121212119</AverageTotalQuantity><AverageTotalRevenue>34.702803030303038</AverageTotalRevenue><Books><Id>19</Id><Name>Hotelík na Islande</Name><TotalQuantity>189</TotalQuantity><TotalRevenue>2678.13</TotalRevenue><AverageTotalQuantity>1.4318181818181819</AverageTotalQuantity><AverageTotalRevenue>20.288863636363637</AverageTotalRevenue></Books><Books><Id>18</Id><Name>Kaviareň v Kodani</Name><TotalQuantity>136</TotalQuantity><TotalRevenue>1902.6400000000008</TotalRevenue><AverageTotalQuantity>1.0303030303030303</AverageTotalQuantity><AverageTotalRevenue>14.4139393939394</AverageTotalRevenue></Books></AggregatedData><AggregatedData><Podkategoria>Andrew Morton</Podkategoria><TotalQuantity>176</TotalQuantity><TotalRevenue>3974.08</TotalRevenue><AverageTotalQuantity>1.3333333333333333</AverageTotalQuantity><AverageTotalRevenue>30.106666666666666</AverageTotalRevenue><Books><Id>22</Id><Name>Diana</Name><TotalQuantity>176</TotalQuantity><TotalRevenue>3974.08</TotalRevenue><AverageTotalQuantity>1.3333333333333333</AverageTotalQuantity><AverageTotalRevenue>30.106666666666666</AverageTotalRevenue></Books></AggregatedData><AggregatedData><Podkategoria>Dominik Dán</Podkategoria><TotalQuantity>381</TotalQuantity><TotalRevenue>3629.400000000001</TotalRevenue><AverageTotalQuantity>2.8863636363636362</AverageTotalQuantity><AverageTotalRevenue>27.495454545454553</AverageTotalRevenue><Books><Id>13</Id><Name>Mucha</Name><TotalQuantity>102</TotalQuantity><TotalRevenue>1524.8999999999999</TotalRevenue><AverageTotalQuantity>0.77272727272727271</AverageTotalQuantity><AverageTotalRevenue>11.552272727272726</AverageTotalRevenue></Books><Books><Id>12</Id><Name>Smrť na druhom brehu</Name><TotalQuantity>86</TotalQuantity><TotalRevenue>1139.5</TotalRevenue><AverageTotalQuantity>0.65151515151515149</AverageTotalQuantity><AverageTotalRevenue>8.6325757575757578</AverageTotalRevenue></Books><Books><Id>11</Id><Name>Tajomný závoj</Name><TotalQuantity>193</TotalQuantity><TotalRevenue>965</TotalRevenue><AverageTotalQuantity>1.4621212121212122</AverageTotalQuantity><AverageTotalRevenue>7.3106060606060606</AverageTotalRevenue></Books></AggregatedData><AggregatedData><Podkategoria>Agatha Christie</Podkategoria><TotalQuantity>360</TotalQuantity><TotalRevenue>3253.8500000000004</TotalRevenue><AverageTotalQuantity>2.7272727272727271</AverageTotalQuantity><AverageTotalRevenue>24.65037878787879</AverageTotalRevenue><Books><Id>15</Id><Name>Veľká štvorka</Name><TotalQuantity>241</TotalQuantity><TotalRevenue>2325.6499999999996</TotalRevenue><AverageTotalQuantity>1.8257575757575757</AverageTotalQuantity><AverageTotalRevenue>17.618560606060605</AverageTotalRevenue></Books><Books><Id>14</Id><Name>Nemý svedok</Name><TotalQuantity>119</TotalQuantity><TotalRevenue>928.2</TotalRevenue><AverageTotalQuantity>0.90151515151515149</AverageTotalQuantity><AverageTotalRevenue>7.0318181818181822</AverageTotalRevenue></Books></AggregatedData><AggregatedData><Podkategoria>J.K. Rowling</Podkategoria><TotalQuantity>239</TotalQuantity><TotalRevenue>3210.3700000000003</TotalRevenue><AverageTotalQuantity>1.8106060606060606</AverageTotalQuantity><AverageTotalRevenue>24.320984848484851</AverageTotalRevenue><Books><Id>1</Id><Name>Harry Potter a Tajomná komnata</Name><TotalQuantity>152</TotalQuantity><TotalRevenue>1808.8000000000002</TotalRevenue><AverageTotalQuantity>1.1515151515151516</AverageTotalQuantity><AverageTotalRevenue>13.703030303030305</AverageTotalRevenue></Books><Books><Id>2</Id><Name>Harry Potter a Ohnivá čaša</Name><TotalQuantity>87</TotalQuantity><TotalRevenue>1401.5699999999997</TotalRevenue><AverageTotalQuantity>0.65909090909090906</AverageTotalQuantity><AverageTotalRevenue>10.617954545454543</AverageTotalRevenue></Books></AggregatedData><AggregatedData><Podkategoria>Arthur C. Clarke</Podkategoria><TotalQuantity>218</TotalQuantity><TotalRevenue>3136.8799999999987</TotalRevenue><AverageTotalQuantity>1.6515151515151516</AverageTotalQuantity><AverageTotalRevenue>23.764242424242415</AverageTotalRevenue><Books><Id>5</Id><Name>Setkání s Rámou</Name><TotalQuantity>108</TotalQuantity><TotalRevenue>1680.4799999999998</TotalRevenue><AverageTotalQuantity>0.81818181818181823</AverageTotalQuantity><AverageTotalRevenue>12.730909090909089</AverageTotalRevenue></Books><Books><Id>6</Id><Name>2010: Druhá vesmírná odysea</Name><TotalQuantity>110</TotalQuantity><TotalRevenue>1456.4000000000003</TotalRevenue><AverageTotalQuantity>0.83333333333333337</AverageTotalQuantity><AverageTotalRevenue>11.033333333333335</AverageTotalRevenue></Books></AggregatedData><AggregatedData><Podkategoria>J.R.R. Tolkien</Podkategoria><TotalQuantity>213</TotalQuantity><TotalRevenue>3079.98</TotalRevenue><AverageTotalQuantity>1.6136363636363635</AverageTotalQuantity><AverageTotalRevenue>23.333181818181817</AverageTotalRevenue><Books><Id>17</Id><Name>Pán prsteňov III. - Návrat kráľa</Name><TotalQuantity>213</TotalQuantity><TotalRevenue>3079.98</TotalRevenue><AverageTotalQuantity>1.6136363636363635</AverageTotalQuantity><AverageTotalRevenue>23.333181818181817</AverageTotalRevenue></Books></AggregatedData><AggregatedData><Podkategoria>Igor Bukovský</Podkategoria><TotalQuantity>119</TotalQuantity><TotalRevenue>2973.81</TotalRevenue><AverageTotalQuantity>0.90151515151515149</AverageTotalQuantity><AverageTotalRevenue>22.528863636363635</AverageTotalRevenue><Books><Id>29</Id><Name>Návod na prežitie pre muža</Name><TotalQuantity>119</TotalQuantity><TotalRevenue>2973.81</TotalRevenue><AverageTotalQuantity>0.90151515151515149</AverageTotalQuantity><AverageTotalRevenue>22.528863636363635</AverageTotalRevenue></Books></AggregatedData><AggregatedData><Podkategoria>Walter Isaacson</Podkategoria><TotalQuantity>123</TotalQuantity><TotalRevenue>2773.65</TotalRevenue><AverageTotalQuantity>0.93181818181818177</AverageTotalQuantity><AverageTotalRevenue>21.0125</AverageTotalRevenue><Books><Id>23</Id><Name>Steve Jobs</Name><TotalQuantity>123</TotalQuantity><TotalRevenue>2773.65</TotalRevenue><AverageTotalQuantity>0.93181818181818177</AverageTotalQuantity><AverageTotalRevenue>21.0125</AverageTotalRevenue></Books></AggregatedData><AggregatedData><Podkategoria>Antoine De Saint-Exupéry</Podkategoria><TotalQuantity>178</TotalQuantity><TotalRevenue>2661.1</TotalRevenue><AverageTotalQuantity>1.3484848484848484</AverageTotalQuantity><AverageTotalRevenue>20.159848484848485</AverageTotalRevenue><Books><Id>25</Id><Name>Malý princ</Name><TotalQuantity>178</TotalQuantity><TotalRevenue>2661.1</TotalRevenue><AverageTotalQuantity>1.3484848484848484</AverageTotalQuantity><AverageTotalRevenue>20.159848484848485</AverageTotalRevenue></Books></AggregatedData><AggregatedData><Podkategoria>Karolína Fourová</Podkategoria><TotalQuantity>127</TotalQuantity><TotalRevenue>2032</TotalRevenue><AverageTotalQuantity>0.96212121212121215</AverageTotalQuantity><AverageTotalRevenue>15.393939393939394</AverageTotalRevenue><Books><Id>4</Id><Name>Jediná kniha o jídle, kterou potřebujete</Name><TotalQuantity>127</TotalQuantity><TotalRevenue>2032</TotalRevenue><AverageTotalQuantity>0.96212121212121215</AverageTotalQuantity><AverageTotalRevenue>15.393939393939394</AverageTotalRevenue></Books></AggregatedData><AggregatedData><Podkategoria>Friedrich Nietzsche</Podkategoria><TotalQuantity>119</TotalQuantity><TotalRevenue>1946.8399999999997</TotalRevenue><AverageTotalQuantity>0.90151515151515149</AverageTotalQuantity><AverageTotalRevenue>14.748787878787876</AverageTotalRevenue><Books><Id>27</Id><Name>Mimo dobro a zlo</Name><TotalQuantity>119</TotalQuantity><TotalRevenue>1946.8399999999997</TotalRevenue><AverageTotalQuantity>0.90151515151515149</AverageTotalQuantity><AverageTotalRevenue>14.748787878787876</AverageTotalRevenue></Books></AggregatedData><AggregatedData><Podkategoria>Nicolas d'Estienne d'Orves</Podkategoria><TotalQuantity>125</TotalQuantity><TotalRevenue>1811.2500000000007</TotalRevenue><AverageTotalQuantity>0.946969696969697</AverageTotalQuantity><AverageTotalRevenue>13.721590909090914</AverageTotalRevenue><Books><Id>16</Id><Name>Eiffel</Name><TotalQuantity>125</TotalQuantity><TotalRevenue>1811.2500000000007</TotalRevenue><AverageTotalQuantity>0.946969696969697</AverageTotalQuantity><AverageTotalRevenue>13.721590909090914</AverageTotalRevenue></Books></AggregatedData><AggregatedData><Podkategoria>Martin Heidegger</Podkategoria><TotalQuantity>117</TotalQuantity><TotalRevenue>1682.46</TotalRevenue><AverageTotalQuantity>0.88636363636363635</AverageTotalQuantity><AverageTotalRevenue>12.745909090909091</AverageTotalRevenue><Books><Id>28</Id><Name>Co znamená myslet?</Name><TotalQuantity>117</TotalQuantity><TotalRevenue>1682.46</TotalRevenue><AverageTotalQuantity>0.88636363636363635</AverageTotalQuantity><AverageTotalRevenue>12.745909090909091</AverageTotalRevenue></Books></AggregatedData><AggregatedData><Podkategoria>Miroslav Virius</Podkategoria><TotalQuantity>88</TotalQuantity><TotalRevenue>1574.3200000000002</TotalRevenue><AverageTotalQuantity>0.66666666666666663</AverageTotalQuantity><AverageTotalRevenue>11.926666666666668</AverageTotalRevenue><Books><Id>8</Id><Name>Programování v C#</Name><TotalQuantity>88</TotalQuantity><TotalRevenue>1574.3200000000002</TotalRevenue><AverageTotalQuantity>0.66666666666666663</AverageTotalQuantity><AverageTotalRevenue>11.926666666666668</AverageTotalRevenue></Books></AggregatedData><AggregatedData><Podkategoria>George Orwell</Podkategoria><TotalQuantity>115</TotalQuantity><TotalRevenue>1477.75</TotalRevenue><AverageTotalQuantity>0.87121212121212122</AverageTotalQuantity><AverageTotalRevenue>11.195075757575758</AverageTotalRevenue><Books><Id>26</Id><Name>1984</Name><TotalQuantity>115</TotalQuantity><TotalRevenue>1477.75</TotalRevenue><AverageTotalQuantity>0.87121212121212122</AverageTotalQuantity><AverageTotalRevenue>11.195075757575758</AverageTotalRevenue></Books></AggregatedData><AggregatedData><Podkategoria>Michaela  Vannini</Podkategoria><TotalQuantity>87</TotalQuantity><TotalRevenue>1283.25</TotalRevenue><AverageTotalQuantity>0.65909090909090906</AverageTotalQuantity><AverageTotalRevenue>9.7215909090909083</AverageTotalRevenue><Books><Id>7</Id><Name>Nová taliančina pre samoukov</Name><TotalQuantity>87</TotalQuantity><TotalRevenue>1283.25</TotalRevenue><AverageTotalQuantity>0.65909090909090906</AverageTotalQuantity><AverageTotalRevenue>9.7215909090909083</AverageTotalRevenue></Books></AggregatedData><AggregatedData><Podkategoria>Zdenka Horecká</Podkategoria><TotalQuantity>59</TotalQuantity><TotalRevenue>678.5</TotalRevenue><AverageTotalQuantity>0.44696969696969696</AverageTotalQuantity><AverageTotalRevenue>5.1401515151515156</AverageTotalRevenue><Books><Id>30</Id><Name>Víkendové varenie</Name><TotalQuantity>59</TotalQuantity><TotalRevenue>678.5</TotalRevenue><AverageTotalQuantity>0.44696969696969696</AverageTotalQuantity><AverageTotalRevenue>5.1401515151515156</AverageTotalRevenue></Books></AggregatedData><AggregatedData><Podkategoria>Mike Shema</Podkategoria><TotalQuantity>319</TotalQuantity><TotalRevenue>11616.5</TotalRevenue><AverageTotalQuantity>2.4166666666666665</AverageTotalQuantity><AverageTotalRevenue>88.003787878787875</AverageTotalRevenue><Books><Id>9</Id><Name>Hacking Web Apps</Name><TotalQuantity>254</TotalQuantity><TotalRevenue>10414</TotalRevenue><AverageTotalQuantity>1.9242424242424243</AverageTotalQuantity><AverageTotalRevenue>78.893939393939391</AverageTotalRevenue></Books><Books><Id>10</Id><Name>Hacking bez tajemství - Webové aplikace</Name><TotalQuantity>65</TotalQuantity><TotalRevenue>1202.5</TotalRevenue><AverageTotalQuantity>0.49242424242424243</AverageTotalQuantity><AverageTotalRevenue>9.1098484848484844</AverageTotalRevenue></Books></AggregatedData><AggregatedData><Podkategoria>Dale Carnegie</Podkategoria><TotalQuantity>364</TotalQuantity><TotalRevenue>6372.2999999999993</TotalRevenue><AverageTotalQuantity>2.7575757575757578</AverageTotalQuantity><AverageTotalRevenue>48.274999999999991</AverageTotalRevenue><Books><Id>21</Id><Name>Ako sa zbaviť starostí a začať žiť</Name><TotalQuantity>218</TotalQuantity><TotalRevenue>4905</TotalRevenue><AverageTotalQuantity>1.6515151515151516</AverageTotalQuantity><AverageTotalRevenue>37.159090909090907</AverageTotalRevenue></Books><Books><Id>20</Id><Name>Ako si získavať priateľov a pôsobiť na ľudí</Name><TotalQuantity>146</TotalQuantity><TotalRevenue>1467.2999999999997</TotalRevenue><AverageTotalQuantity>1.106060606060606</AverageTotalQuantity><AverageTotalRevenue>11.115909090909089</AverageTotalRevenue></Books></AggregatedData><AggregatedData><Podkategoria>Jaroslava Lukačovičová</Podkategoria><TotalQuantity>324</TotalQuantity><TotalRevenue>4879.2800000000016</TotalRevenue><AverageTotalQuantity>2.4545454545454546</AverageTotalQuantity><AverageTotalRevenue>36.964242424242435</AverageTotalRevenue><Books><Id>24</Id><Name>Šlabikár financií pre neziskovky</Name><TotalQuantity>188</TotalQuantity><TotalRevenue>3568.2400000000002</TotalRevenue><AverageTotalQuantity>1.4242424242424243</AverageTotalQuantity><AverageTotalRevenue>27.032121212121215</AverageTotalRevenue></Books><Books><Id>3</Id><Name>Jednoduché účtovníctvo pre neziskovky</Name><TotalQuantity>136</TotalQuantity><TotalRevenue>1311.04</TotalRevenue><AverageTotalQuantity>1.0303030303030303</AverageTotalQuantity><AverageTotalRevenue>9.9321212121212117</AverageTotalRevenue></Books></AggregatedData><AggregatedData><Podkategoria>Julie Caplin</Podkategoria><TotalQuantity>325</TotalQuantity><TotalRevenue>4580.7700000000013</TotalRevenue><AverageTotalQuantity>2.4621212121212119</AverageTotalQuantity><AverageTotalRevenue>34.702803030303038</AverageTotalRevenue><Books><Id>19</Id><Name>Hotelík na Islande</Name><TotalQuantity>189</TotalQuantity><TotalRevenue>2678.13</TotalRevenue><AverageTotalQuantity>1.4318181818181819</AverageTotalQuantity><AverageTotalRevenue>20.288863636363637</AverageTotalRevenue></Books><Books><Id>18</Id><Name>Kaviareň v Kodani</Name><TotalQuantity>136</TotalQuantity><TotalRevenue>1902.6400000000008</TotalRevenue><AverageTotalQuantity>1.0303030303030303</AverageTotalQuantity><AverageTotalRevenue>14.4139393939394</AverageTotalRevenue></Books></AggregatedData><AggregatedData><Podkategoria>Andrew Morton</Podkategoria><TotalQuantity>176</TotalQuantity><TotalRevenue>3974.08</TotalRevenue><AverageTotalQuantity>1.3333333333333333</AverageTotalQuantity><AverageTotalRevenue>30.106666666666666</AverageTotalRevenue><Books><Id>22</Id><Name>Diana</Name><TotalQuantity>176</TotalQuantity><TotalRevenue>3974.08</TotalRevenue><AverageTotalQuantity>1.3333333333333333</AverageTotalQuantity><AverageTotalRevenue>30.106666666666666</AverageTotalRevenue></Books></AggregatedData><AggregatedData><Podkategoria>Dominik Dán</Podkategoria><TotalQuantity>381</TotalQuantity><TotalRevenue>3629.400000000001</TotalRevenue><AverageTotalQuantity>2.8863636363636362</AverageTotalQuantity><AverageTotalRevenue>27.495454545454553</AverageTotalRevenue><Books><Id>13</Id><Name>Mucha</Name><TotalQuantity>102</TotalQuantity><TotalRevenue>1524.8999999999999</TotalRevenue><AverageTotalQuantity>0.77272727272727271</AverageTotalQuantity><AverageTotalRevenue>11.552272727272726</AverageTotalRevenue></Books><Books><Id>12</Id><Name>Smrť na druhom brehu</Name><TotalQuantity>86</TotalQuantity><TotalRevenue>1139.5</TotalRevenue><AverageTotalQuantity>0.65151515151515149</AverageTotalQuantity><AverageTotalRevenue>8.6325757575757578</AverageTotalRevenue></Books><Books><Id>11</Id><Name>Tajomný závoj</Name><TotalQuantity>193</TotalQuantity><TotalRevenue>965</TotalRevenue><AverageTotalQuantity>1.4621212121212122</AverageTotalQuantity><AverageTotalRevenue>7.3106060606060606</AverageTotalRevenue></Books></AggregatedData><AggregatedData><Podkategoria>Agatha Christie</Podkategoria><TotalQuantity>360</TotalQuantity><TotalRevenue>3253.8500000000004</TotalRevenue><AverageTotalQuantity>2.7272727272727271</AverageTotalQuantity><AverageTotalRevenue>24.65037878787879</AverageTotalRevenue><Books><Id>15</Id><Name>Veľká štvorka</Name><TotalQuantity>241</TotalQuantity><TotalRevenue>2325.6499999999996</TotalRevenue><AverageTotalQuantity>1.8257575757575757</AverageTotalQuantity><AverageTotalRevenue>17.618560606060605</AverageTotalRevenue></Books><Books><Id>14</Id><Name>Nemý svedok</Name><TotalQuantity>119</TotalQuantity><TotalRevenue>928.2</TotalRevenue><AverageTotalQuantity>0.90151515151515149</AverageTotalQuantity><AverageTotalRevenue>7.0318181818181822</AverageTotalRevenue></Books></AggregatedData><AggregatedData><Podkategoria>J.K. Rowling</Podkategoria><TotalQuantity>239</TotalQuantity><TotalRevenue>3210.3700000000003</TotalRevenue><AverageTotalQuantity>1.8106060606060606</AverageTotalQuantity><AverageTotalRevenue>24.320984848484851</AverageTotalRevenue><Books><Id>1</Id><Name>Harry Potter a Tajomná komnata</Name><TotalQuantity>152</TotalQuantity><TotalRevenue>1808.8000000000002</TotalRevenue><AverageTotalQuantity>1.1515151515151516</AverageTotalQuantity><AverageTotalRevenue>13.703030303030305</AverageTotalRevenue></Books><Books><Id>2</Id><Name>Harry Potter a Ohnivá čaša</Name><TotalQuantity>87</TotalQuantity><TotalRevenue>1401.5699999999997</TotalRevenue><AverageTotalQuantity>0.65909090909090906</AverageTotalQuantity><AverageTotalRevenue>10.617954545454543</AverageTotalRevenue></Books></AggregatedData><AggregatedData><Podkategoria>Arthur C. Clarke</Podkategoria><TotalQuantity>218</TotalQuantity><TotalRevenue>3136.8799999999987</TotalRevenue><AverageTotalQuantity>1.6515151515151516</AverageTotalQuantity><AverageTotalRevenue>23.764242424242415</AverageTotalRevenue><Books><Id>5</Id><Name>Setkání s Rámou</Name><TotalQuantity>108</TotalQuantity><TotalRevenue>1680.4799999999998</TotalRevenue><AverageTotalQuantity>0.81818181818181823</AverageTotalQuantity><AverageTotalRevenue>12.730909090909089</AverageTotalRevenue></Books><Books><Id>6</Id><Name>2010: Druhá vesmírná odysea</Name><TotalQuantity>110</TotalQuantity><TotalRevenue>1456.4000000000003</TotalRevenue><AverageTotalQuantity>0.83333333333333337</AverageTotalQuantity><AverageTotalRevenue>11.033333333333335</AverageTotalRevenue></Books></AggregatedData><AggregatedData><Podkategoria>J.R.R. Tolkien</Podkategoria><TotalQuantity>213</TotalQuantity><TotalRevenue>3079.98</TotalRevenue><AverageTotalQuantity>1.6136363636363635</AverageTotalQuantity><AverageTotalRevenue>23.333181818181817</AverageTotalRevenue><Books><Id>17</Id><Name>Pán prsteňov III. - Návrat kráľa</Name><TotalQuantity>213</TotalQuantity><TotalRevenue>3079.98</TotalRevenue><AverageTotalQuantity>1.6136363636363635</AverageTotalQuantity><AverageTotalRevenue>23.333181818181817</AverageTotalRevenue></Books></AggregatedData><AggregatedData><Podkategoria>Igor Bukovský</Podkategoria><TotalQuantity>119</TotalQuantity><TotalRevenue>2973.81</TotalRevenue><AverageTotalQuantity>0.90151515151515149</AverageTotalQuantity><AverageTotalRevenue>22.528863636363635</AverageTotalRevenue><Books><Id>29</Id><Name>Návod na prežitie pre muža</Name><TotalQuantity>119</TotalQuantity><TotalRevenue>2973.81</TotalRevenue><AverageTotalQuantity>0.90151515151515149</AverageTotalQuantity><AverageTotalRevenue>22.528863636363635</AverageTotalRevenue></Books></AggregatedData><AggregatedData><Podkategoria>Walter Isaacson</Podkategoria><TotalQuantity>123</TotalQuantity><TotalRevenue>2773.65</TotalRevenue><AverageTotalQuantity>0.93181818181818177</AverageTotalQuantity><AverageTotalRevenue>21.0125</AverageTotalRevenue><Books><Id>23</Id><Name>Steve Jobs</Name><TotalQuantity>123</TotalQuantity><TotalRevenue>2773.65</TotalRevenue><AverageTotalQuantity>0.93181818181818177</AverageTotalQuantity><AverageTotalRevenue>21.0125</AverageTotalRevenue></Books></AggregatedData><AggregatedData><Podkategoria>Antoine De Saint-Exupéry</Podkategoria><TotalQuantity>178</TotalQuantity><TotalRevenue>2661.1</TotalRevenue><AverageTotalQuantity>1.3484848484848484</AverageTotalQuantity><AverageTotalRevenue>20.159848484848485</AverageTotalRevenue><Books><Id>25</Id><Name>Malý princ</Name><TotalQuantity>178</TotalQuantity><TotalRevenue>2661.1</TotalRevenue><AverageTotalQuantity>1.3484848484848484</AverageTotalQuantity><AverageTotalRevenue>20.159848484848485</AverageTotalRevenue></Books></AggregatedData><AggregatedData><Podkategoria>Karolína Fourová</Podkategoria><TotalQuantity>127</TotalQuantity><TotalRevenue>2032</TotalRevenue><AverageTotalQuantity>0.96212121212121215</AverageTotalQuantity><AverageTotalRevenue>15.393939393939394</AverageTotalRevenue><Books><Id>4</Id><Name>Jediná kniha o jídle, kterou potřebujete</Name><TotalQuantity>127</TotalQuantity><TotalRevenue>2032</TotalRevenue><AverageTotalQuantity>0.96212121212121215</AverageTotalQuantity><AverageTotalRevenue>15.393939393939394</AverageTotalRevenue></Books></AggregatedData><AggregatedData><Podkategoria>Friedrich Nietzsche</Podkategoria><TotalQuantity>119</TotalQuantity><TotalRevenue>1946.8399999999997</TotalRevenue><AverageTotalQuantity>0.90151515151515149</AverageTotalQuantity><AverageTotalRevenue>14.748787878787876</AverageTotalRevenue><Books><Id>27</Id><Name>Mimo dobro a zlo</Name><TotalQuantity>119</TotalQuantity><TotalRevenue>1946.8399999999997</TotalRevenue><AverageTotalQuantity>0.90151515151515149</AverageTotalQuantity><AverageTotalRevenue>14.748787878787876</AverageTotalRevenue></Books></AggregatedData><AggregatedData><Podkategoria>Nicolas d'Estienne d'Orves</Podkategoria><TotalQuantity>125</TotalQuantity><TotalRevenue>1811.2500000000007</TotalRevenue><AverageTotalQuantity>0.946969696969697</AverageTotalQuantity><AverageTotalRevenue>13.721590909090914</AverageTotalRevenue><Books><Id>16</Id><Name>Eiffel</Name><TotalQuantity>125</TotalQuantity><TotalRevenue>1811.2500000000007</TotalRevenue><AverageTotalQuantity>0.946969696969697</AverageTotalQuantity><AverageTotalRevenue>13.721590909090914</AverageTotalRevenue></Books></AggregatedData><AggregatedData><Podkategoria>Martin Heidegger</Podkategoria><TotalQuantity>117</TotalQuantity><TotalRevenue>1682.46</TotalRevenue><AverageTotalQuantity>0.88636363636363635</AverageTotalQuantity><AverageTotalRevenue>12.745909090909091</AverageTotalRevenue><Books><Id>28</Id><Name>Co znamená myslet?</Name><TotalQuantity>117</TotalQuantity><TotalRevenue>1682.46</TotalRevenue><AverageTotalQuantity>0.88636363636363635</AverageTotalQuantity><AverageTotalRevenue>12.745909090909091</AverageTotalRevenue></Books></AggregatedData><AggregatedData><Podkategoria>Miroslav Virius</Podkategoria><TotalQuantity>88</TotalQuantity><TotalRevenue>1574.3200000000002</TotalRevenue><AverageTotalQuantity>0.66666666666666663</AverageTotalQuantity><AverageTotalRevenue>11.926666666666668</AverageTotalRevenue><Books><Id>8</Id><Name>Programování v C#</Name><TotalQuantity>88</TotalQuantity><TotalRevenue>1574.3200000000002</TotalRevenue><AverageTotalQuantity>0.66666666666666663</AverageTotalQuantity><AverageTotalRevenue>11.926666666666668</AverageTotalRevenue></Books></AggregatedData><AggregatedData><Podkategoria>George Orwell</Podkategoria><TotalQuantity>115</TotalQuantity><TotalRevenue>1477.75</TotalRevenue><AverageTotalQuantity>0.87121212121212122</AverageTotalQuantity><AverageTotalRevenue>11.195075757575758</AverageTotalRevenue><Books><Id>26</Id><Name>1984</Name><TotalQuantity>115</TotalQuantity><TotalRevenue>1477.75</TotalRevenue><AverageTotalQuantity>0.87121212121212122</AverageTotalQuantity><AverageTotalRevenue>11.195075757575758</AverageTotalRevenue></Books></AggregatedData><AggregatedData><Podkategoria>Michaela  Vannini</Podkategoria><TotalQuantity>87</TotalQuantity><TotalRevenue>1283.25</TotalRevenue><AverageTotalQuantity>0.65909090909090906</AverageTotalQuantity><AverageTotalRevenue>9.7215909090909083</AverageTotalRevenue><Books><Id>7</Id><Name>Nová taliančina pre samoukov</Name><TotalQuantity>87</TotalQuantity><TotalRevenue>1283.25</TotalRevenue><AverageTotalQuantity>0.65909090909090906</AverageTotalQuantity><AverageTotalRevenue>9.7215909090909083</AverageTotalRevenue></Books></AggregatedData><AggregatedData><Podkategoria>Zdenka Horecká</Podkategoria><TotalQuantity>59</TotalQuantity><TotalRevenue>678.5</TotalRevenue><AverageTotalQuantity>0.44696969696969696</AverageTotalQuantity><AverageTotalRevenue>5.1401515151515156</AverageTotalRevenue><Books><Id>30</Id><Name>Víkendové varenie</Name><TotalQuantity>59</TotalQuantity><TotalRevenue>678.5</TotalRevenue><AverageTotalQuantity>0.44696969696969696</AverageTotalQuantity><AverageTotalRevenue>5.1401515151515156</AverageTotalRevenue></Books></AggregatedData><TotalAggregatedData><totalQuantity>4176</totalQuantity><totalRevenue>68628.34</totalRevenue><averageTotalDailyQuantity>31.636363636363637</averageTotalDailyQuantity><averageTotalDailyRevenue>519.91166666666663</averageTotalDailyRevenue><namePodkategoriaMaxRevenue>Mike Shema</namePodkategoriaMaxRevenue><maxRevenuePodkategoria>11616.5</maxRevenuePodkategoria><namePodkategoriaMinRevenue>Zdenka Horecká</namePodkategoriaMinRevenue><minRevenuePodkategoria>678.5</minRevenuePodkategoria><namePodkategoriaMaxQuantity>Dominik Dán</namePodkategoriaMaxQuantity><maxQuantityPodkategoria>381</maxQuantityPodkategoria><namePodkategoriaMinQuantity>Zdenka Horecká</namePodkategoriaMinQuantity><minQuantityPodkategoria>59</minQuantityPodkategoria><nameBookMaxRevenue>Hacking Web Apps</nameBookMaxRevenue><maxRevenueBook>10414</maxRevenueBook><nameBookMinRevenue>Víkendové varenie</nameBookMinRevenue><minRevenueBook>678.5</minRevenueBook><nameBookMaxQuantity>Hacking Web Apps</nameBookMaxQuantity><maxQuantityBook>254</maxQuantityBook><nameBookMinQuantity>Víkendové varenie</nameBookMinQuantity><minQuantityBook>59</minQuantityBook></TotalAggregatedData></Root>