<Root><AggregatedData><Podkategoria>cz</Podkategoria><TotalQuantity>36</TotalQuantity><TotalRevenue>628.94</TotalRevenue><AverageTotalQuantity>12</AverageTotalQuantity><AverageTotalRevenue>209.64666666666668</AverageTotalRevenue><Books><Id>22</Id><Name>Diana</Name><TotalQuantity>9</TotalQuantity><TotalRevenue>203.22</TotalRevenue><AverageTotalQuantity>3</AverageTotalQuantity><AverageTotalRevenue>67.74</AverageTotalRevenue></Books><Books><Id>27</Id><Name>Mimo dobro a zlo</Name><TotalQuantity>7</TotalQuantity><TotalRevenue>114.52</TotalRevenue><AverageTotalQuantity>2.3333333333333335</AverageTotalQuantity><AverageTotalRevenue>38.173333333333332</AverageTotalRevenue></Books><Books><Id>5</Id><Name>Setkání s Rámou</Name><TotalQuantity>20</TotalQuantity><TotalRevenue>311.2</TotalRevenue><AverageTotalQuantity>6.666666666666667</AverageTotalQuantity><AverageTotalRevenue>103.73333333333333</AverageTotalRevenue></Books></AggregatedData><AggregatedData><Podkategoria>en</Podkategoria><TotalQuantity>17</TotalQuantity><TotalRevenue>697</TotalRevenue><AverageTotalQuantity>5.666666666666667</AverageTotalQuantity><AverageTotalRevenue>232.33333333333334</AverageTotalRevenue><Books><Id>9</Id><Name>Hacking Web Apps</Name><TotalQuantity>17</TotalQuantity><TotalRevenue>697</TotalRevenue><AverageTotalQuantity>5.666666666666667</AverageTotalQuantity><AverageTotalRevenue>232.33333333333334</AverageTotalRevenue></Books></AggregatedData><AggregatedData><Podkategoria>sk</Podkategoria><TotalQuantity>99</TotalQuantity><TotalRevenue>1262</TotalRevenue><AverageTotalQuantity>33</AverageTotalQuantity><AverageTotalRevenue>420.66666666666669</AverageTotalRevenue><Books><Id>1</Id><Name>Harry Potter a Tajomná komnata</Name><TotalQuantity>16</TotalQuantity><TotalRevenue>190.4</TotalRevenue><AverageTotalQuantity>5.333333333333333</AverageTotalQuantity><AverageTotalRevenue>63.466666666666669</AverageTotalRevenue></Books><Books><Id>19</Id><Name>Hotelík na Islande</Name><TotalQuantity>8</TotalQuantity><TotalRevenue>113.36</TotalRevenue><AverageTotalQuantity>2.6666666666666665</AverageTotalQuantity><AverageTotalRevenue>37.786666666666669</AverageTotalRevenue></Books><Books><Id>3</Id><Name>Jednoduché účtovníctvo pre neziskovky</Name><TotalQuantity>1</TotalQuantity><TotalRevenue>9.64</TotalRevenue><AverageTotalQuantity>0.33333333333333331</AverageTotalQuantity><AverageTotalRevenue>3.2133333333333334</AverageTotalRevenue></Books><Books><Id>18</Id><Name>Kaviareň v Kodani</Name><TotalQuantity>1</TotalQuantity><TotalRevenue>13.99</TotalRevenue><AverageTotalQuantity>0.33333333333333331</AverageTotalQuantity><AverageTotalRevenue>4.6633333333333331</AverageTotalRevenue></Books><Books><Id>25</Id><Name>Malý princ</Name><TotalQuantity>7</TotalQuantity><TotalRevenue>104.65</TotalRevenue><AverageTotalQuantity>2.3333333333333335</AverageTotalQuantity><AverageTotalRevenue>34.883333333333333</AverageTotalRevenue></Books><Books><Id>29</Id><Name>Návod na prežitie pre muža</Name><TotalQuantity>4</TotalQuantity><TotalRevenue>99.96</TotalRevenue><AverageTotalQuantity>1.3333333333333333</AverageTotalQuantity><AverageTotalRevenue>33.32</AverageTotalRevenue></Books><Books><Id>12</Id><Name>Smrť na druhom brehu</Name><TotalQuantity>29</TotalQuantity><TotalRevenue>384.25</TotalRevenue><AverageTotalQuantity>9.6666666666666661</AverageTotalQuantity><AverageTotalRevenue>128.08333333333334</AverageTotalRevenue></Books><Books><Id>23</Id><Name>Steve Jobs</Name><TotalQuantity>5</TotalQuantity><TotalRevenue>112.75</TotalRevenue><AverageTotalQuantity>1.6666666666666667</AverageTotalQuantity><AverageTotalRevenue>37.583333333333336</AverageTotalRevenue></Books><Books><Id>11</Id><Name>Tajomný závoj</Name><TotalQuantity>8</TotalQuantity><TotalRevenue>40</TotalRevenue><AverageTotalQuantity>2.6666666666666665</AverageTotalQuantity><AverageTotalRevenue>13.333333333333334</AverageTotalRevenue></Books><Books><Id>15</Id><Name>Veľká štvorka</Name><TotalQuantity>20</TotalQuantity><TotalRevenue>193</TotalRevenue><AverageTotalQuantity>6.666666666666667</AverageTotalQuantity><AverageTotalRevenue>64.333333333333329</AverageTotalRevenue></Books></AggregatedData><TotalAggregatedData><totalQuantity>152</totalQuantity><totalRevenue>2587.94</totalRevenue><averageTotalDailyQuantity>50.666666666666664</averageTotalDailyQuantity><averageTotalDailyRevenue>862.64666666666665</averageTotalDailyRevenue><namePodkategoriaMaxRevenue>sk</namePodkategoriaMaxRevenue><maxRevenuePodkategoria>1262</maxRevenuePodkategoria><namePodkategoriaMinRevenue>cz</namePodkategoriaMinRevenue><minRevenuePodkategoria>628.94</minRevenuePodkategoria><namePodkategoriaMaxQuantity>sk</namePodkategoriaMaxQuantity><maxQuantityPodkategoria>99</maxQuantityPodkategoria><namePodkategoriaMinQuantity>en</namePodkategoriaMinQuantity><minQuantityPodkategoria>17</minQuantityPodkategoria><nameBookMaxRevenue>Hacking Web Apps</nameBookMaxRevenue><maxRevenueBook>697</maxRevenueBook><nameBookMinRevenue>Jednoduché účtovníctvo pre neziskovky</nameBookMinRevenue><minRevenueBook>9.64</minRevenueBook><nameBookMaxQuantity>Smrť na druhom brehu</nameBookMaxQuantity><maxQuantityBook>29</maxQuantityBook><nameBookMinQuantity>Jednoduché účtovníctvo pre neziskovky</nameBookMinQuantity><minQuantityBook>1</minQuantityBook></TotalAggregatedData></Root>